odoo/addons/account_due_list_days_overdue/README.rst
odoo/addons/account_due_list_days_overdue/__init__.py
odoo/addons/account_due_list_days_overdue/__manifest__.py
odoo/addons/account_due_list_days_overdue/demo/account_overdue_term_demo.xml
odoo/addons/account_due_list_days_overdue/i18n/account_due_list_days_overdue.pot
odoo/addons/account_due_list_days_overdue/i18n/am.po
odoo/addons/account_due_list_days_overdue/i18n/ar.po
odoo/addons/account_due_list_days_overdue/i18n/bg.po
odoo/addons/account_due_list_days_overdue/i18n/bs.po
odoo/addons/account_due_list_days_overdue/i18n/ca.po
odoo/addons/account_due_list_days_overdue/i18n/cs.po
odoo/addons/account_due_list_days_overdue/i18n/da.po
odoo/addons/account_due_list_days_overdue/i18n/de.po
odoo/addons/account_due_list_days_overdue/i18n/el_GR.po
odoo/addons/account_due_list_days_overdue/i18n/en_GB.po
odoo/addons/account_due_list_days_overdue/i18n/es.po
odoo/addons/account_due_list_days_overdue/i18n/es_AR.po
odoo/addons/account_due_list_days_overdue/i18n/es_CL.po
odoo/addons/account_due_list_days_overdue/i18n/es_CO.po
odoo/addons/account_due_list_days_overdue/i18n/es_CR.po
odoo/addons/account_due_list_days_overdue/i18n/es_DO.po
odoo/addons/account_due_list_days_overdue/i18n/es_EC.po
odoo/addons/account_due_list_days_overdue/i18n/es_ES.po
odoo/addons/account_due_list_days_overdue/i18n/es_MX.po
odoo/addons/account_due_list_days_overdue/i18n/es_PE.po
odoo/addons/account_due_list_days_overdue/i18n/es_PY.po
odoo/addons/account_due_list_days_overdue/i18n/es_VE.po
odoo/addons/account_due_list_days_overdue/i18n/et.po
odoo/addons/account_due_list_days_overdue/i18n/eu.po
odoo/addons/account_due_list_days_overdue/i18n/fa.po
odoo/addons/account_due_list_days_overdue/i18n/fi.po
odoo/addons/account_due_list_days_overdue/i18n/fr.po
odoo/addons/account_due_list_days_overdue/i18n/fr_CA.po
odoo/addons/account_due_list_days_overdue/i18n/fr_CH.po
odoo/addons/account_due_list_days_overdue/i18n/gl.po
odoo_addon_account_due_list_days_overdue-16.0.1.0.0.6.dist-info/METADATA
odoo_addon_account_due_list_days_overdue-16.0.1.0.0.6.dist-info/WHEEL
odoo_addon_account_due_list_days_overdue-16.0.1.0.0.6.dist-info/top_level.txt
odoo_addon_account_due_list_days_overdue-16.0.1.0.0.6.dist-info/RECORD
