Metadata-Version: 2.1
Name: odoo-addon-account_due_list_days_overdue
Version: 16.0.1.0.0.6
Summary: Payments Due list days overdue
Home-page: https://github.com/OCA/account-payment
Author: Odoo Community Association (OCA), ForgeFlow
Author-email: support@odoo-community.org
License: AGPL-3
Classifier: Programming Language :: Python
Classifier: Framework :: Odoo
Classifier: Framework :: Odoo :: 16.0
Classifier: License :: OSI Approved :: GNU Affero General Public License v3
Requires-Python: >=3.10
Requires-Dist: odoo-addon-account-due-list<16.1dev,>=16.0dev
Requires-Dist: odoo<16.1dev,>=16.0a
